{
  "type": "Feature",
  "id": "SHMK",
  "properties": {
    "name": "寺河煤矿"
  },
  "geometry": {
    "type": "Polygon",
    "coordinates": [
      [
        [
          112.6445750,
          35.5815800
        ],
        [
          112.6032340,
          35.5917660
        ],
        [
          112.5989120,
          35.5817940
        ],
        [
          112.5763880,
          35.5815310
        ],
        [
          112.5729960,
          35.5760910
        ],
        [
          112.5351710,
          35.5897950
        ],
        [
          112.5355280,
          35.5985720
        ],
        [
          112.5360440,
          35.5983670
        ],
        [
          112.5821960,
          35.5989090
        ],
        [
          112.5820500,
          35.6070640
        ],
        [
          112.6101260,
          35.6073890
        ],
        [
          112.6342000,
          35.6590360
        ],
        [
          112.6269850,
          35.6659440
        ],
        [
          112.5283150,
          35.6647760
        ],
        [
          112.5287520,
          35.6209570
        ],
        [
          112.5221270,
          35.6203060
        ],
        [
          112.5269290,
          35.5809350
        ],
        [
          112.5311800,
          35.5874950
        ],
        [
          112.5334570,
          35.5865800
        ],
        [
          112.5346870,
          35.5869580
        ],
        [
          112.5853370,
          35.5686710
        ],
        [
          112.5828080,
          35.5659240
        ],
        [
          112.5847980,
          35.5652220
        ],
        [
          112.5844440,
          35.5570180
        ],
        [
          112.5885730,
          35.5554870
        ],
        [
          112.5863790,
          35.5514330
        ],
        [
          112.5908700,
          35.5497230
        ],
        [
          112.5909050,
          35.5478690
        ],
        [
          112.5985050,
          35.5468890
        ],
        [
          112.5984750,
          35.5496020
        ],
        [
          112.6133360,
          35.5458470
        ],
        [
          112.6188590,
          35.5453190
        ],
        [
          112.6232060,
          35.5438910
        ],
        [
          112.6265540,
          35.5496550
        ],
        [
          112.6342100,
          35.5479990
        ],
        [
          112.6370270,
          35.5554290
        ],
        [
          112.6368570,
          35.5639620
        ],
        [
          112.6382910,
          35.5699630
        ],
        [
          112.6445750,
          35.5815800
        ]
      ]
    ]
  }
}
